mocha/__init__.py
mocha/__main__.py
mocha/commands/__init__.py
mocha/commands/coffee.py
mocha/commands/greet.py
mocha/commands/hydrate.py
mocha/commands/note.py
mocha/commands/timer.py
mocha/commands/todo.py
mocha_sh-1.0.5.dist-info/licenses/LICENSE
mocha_sh-1.0.5.dist-info/METADATA
mocha_sh-1.0.5.dist-info/WHEEL
mocha_sh-1.0.5.dist-info/entry_points.txt
mocha_sh-1.0.5.dist-info/top_level.txt
mocha_sh-1.0.5.dist-info/RECORD
