Metadata-Version: 2.4
Name: mocha-sh
Version: 1.0.5
Summary: ☕ Mocha.sh — your cozy terminal companion
Author: Robin Engels
License: MIT
Project-URL: Homepage, https://github.com/Mocha-sh/Mocha
Project-URL: Issues, https://github.com/Mocha-sh/Mocha/issues
Requires-Python: >=3.8
License-File: LICENSE
Requires-Dist: click>=8.1
Requires-Dist: rich>=13.0
Requires-Dist: colorama>=0.4
Requires-Dist: InquirerPy>=0.3
Requires-Dist: textual>=0.62
Requires-Dist: pygments>=2.17
Dynamic: license-file
